importsinjson/__init__.py
importsinjson-0.1.1.dist-info/METADATA
importsinjson-0.1.1.dist-info/LICENSE
importsinjson-0.1.1.dist-info/WHEEL
importsinjson-0.1.1.dist-info/RECORD
