Metadata-Version: 2.1
Name: importsinjson
Version: 0.1.1
Summary: Adding import functionality to JSON files
Home-page: https://github.com/NathanVaughn/importsinjson
License: MIT
Author: Nathan Vaughn
Author-email: nvaughn51@gmail.com
Requires-Python: >=3.7,<4.0
Classifier: Intended Audience :: Developers
Classifier: License :: OSI Approved :: MIT License
Classifier: Programming Language :: Python :: 3
Classifier: Programming Language :: Python :: 3.7
Classifier: Programming Language :: Python :: 3.8
Classifier: Programming Language :: Python :: 3.9
Classifier: Programming Language :: Python :: 3.10
Classifier: Programming Language :: Python :: 3.11
Classifier: Topic :: Software Development :: Libraries :: Python Modules
Classifier: Topic :: Text Processing
Provides-Extra: commentjson
Provides-Extra: pyjson5
Requires-Dist: commentjson (>=0.9.0,<0.10.0) ; extra == "commentjson"
Requires-Dist: pyjson5 (>=1.6.1,<2.0.0) ; extra == "pyjson5"
Project-URL: Issues, https://github.com/NathanVaughn/importsinjson/issues
Project-URL: Repository, https://github.com/NathanVaughn/importsinjson.git
